b10_tcache/__init__.py
b10_tcache/archive.py
b10_tcache/core.py
b10_tcache/environment.py
b10_tcache/info.py
b10_tcache/utils.py
baseten_tcache-0.0.1.dist-info/METADATA
baseten_tcache-0.0.1.dist-info/WHEEL
baseten_tcache-0.0.1.dist-info/RECORD
