Metadata-Version: 2.3
Name: baseten-tcache
Version: 0.0.1
Summary: Distributed PyTorch compilation cache for Baseten - Environment-aware, lock-free compilation cache management
License: MIT
Keywords: pytorch,torch.compile,cache,machine-learning,inference
Author: Shounak Ray
Author-email: shounak@baseten.co
Requires-Python: >=3.9,<4.0
Classifier: Development Status :: 4 - Beta
Classifier: Intended Audience :: Developers
Classifier: License :: OSI Approved :: MIT License
Classifier: Programming Language :: Python :: 3
Classifier: Programming Language :: Python :: 3.9
Classifier: Programming Language :: Python :: 3.10
Classifier: Programming Language :: Python :: 3.11
Classifier: Programming Language :: Python :: 3.12
Classifier: Programming Language :: Python :: 3.13
Classifier: Topic :: Scientific/Engineering :: Artificial Intelligence
Classifier: Topic :: Software Development :: Libraries :: Python Modules
Requires-Dist: torch (>=2.0.0)
Requires-Dist: triton (>=2.0.0)
Project-URL: Documentation, https://docs.baseten.co/development/model/b10-tcache
Project-URL: Homepage, https://docs.baseten.co/development/model/b10-tcache
Project-URL: Repository, https://pypi.org/project/b10-tcache/
